pyleak/__init__.py
pyleak/base.py
pyleak/combined.py
pyleak/eventloop.py
pyleak/pytest_plugin.py
pyleak/tasks.py
pyleak/threads.py
pyleak/utils.py
pyleak-0.1.14.dist-info/METADATA
pyleak-0.1.14.dist-info/WHEEL
pyleak-0.1.14.dist-info/entry_points.txt
pyleak-0.1.14.dist-info/licenses/LICENSE
pyleak-0.1.14.dist-info/RECORD
