Metadata-Version: 2.4
Name: pyleak
Version: 0.1.14
Summary: Detect leaked asyncio tasks, threads, and event loop blocking in Python. Inspired by Go's goleak
Project-URL: Homepage, https://github.com/deepankarm/pyleak
Project-URL: Repository, https://github.com/deepankarm/pyleak
Project-URL: Issues, https://github.com/deepankarm/pyleak/issues
Author-email: Deepankar Mahapatro <deepankarmahapatro@gmail.com>
License-File: LICENSE
Keywords: async,asyncio,goleak,leak,pytest,tasks,testing,threads
Requires-Python: >=3.9
Requires-Dist: exceptiongroup>=1.3.0
